rerole_lib/__init__.py
rerole_lib/ability.py
rerole_lib/character.py
rerole_lib/effect.py
rerole_lib/save.py
rerole_lib/skill.py
rerole_lib/utils.py
rerole_lib-0.8.0.dist-info/METADATA
rerole_lib-0.8.0.dist-info/WHEEL
rerole_lib-0.8.0.dist-info/RECORD
