Metadata-Version: 2.1
Name: rerole-lib
Version: 0.8.0
Summary: A library for interacting with Pathfinder 1E character sheet data.
Author: Matt Hale
Author-email: matthew.hale@protonmail.com
Requires-Python: >=3.12,<4.0
Classifier: Programming Language :: Python :: 3
Classifier: Programming Language :: Python :: 3.12
